elastic_doc_manager-0.3.0.dist-info/DESCRIPTION.rst
elastic_doc_manager-0.3.0.dist-info/METADATA
elastic_doc_manager-0.3.0.dist-info/RECORD
elastic_doc_manager-0.3.0.dist-info/WHEEL
elastic_doc_manager-0.3.0.dist-info/metadata.json
elastic_doc_manager-0.3.0.dist-info/top_level.txt
mongo_connector/__init__.py
mongo_connector/doc_managers/__init__.py
mongo_connector/doc_managers/elastic_doc_manager.py
