Metadata-Version: 2.0
Name: elastic-doc-manager
Version: 0.3.0
Summary: Elastic 1.x plugin for mongo-connector
Home-page: https://github.com/mongodb-labs/elastic-doc-manager
Author: mongodb
Author-email: mongodb-user@googlegroups.com
License: Apache License, Version 2.0
Keywords: mongo-connector,mongodb,elastic,elasticsearch
Platform: any
Classifier: Development Status :: 4 - Beta
Classifier: Intended Audience :: Developers
Classifier: License :: OSI Approved :: Apache Software License
Classifier: Programming Language :: Python :: 2.6
Classifier: Programming Language :: Python :: 2.7
Classifier: Programming Language :: Python :: 3.3
Classifier: Programming Language :: Python :: 3.4
Classifier: Topic :: Database
Classifier: Topic :: Software Development :: Libraries :: Python Modules
Classifier: Operating System :: Unix
Classifier: Operating System :: MacOS :: MacOS X
Classifier: Operating System :: Microsoft :: Windows
Classifier: Operating System :: POSIX
Requires-Dist: mongo-connector (>=2.5.0)
Requires-Dist: elasticsearch (<2.0.0,>=1.2)
Provides-Extra: aws
Requires-Dist: boto3 (>=1.4.0); extra == 'aws'
Requires-Dist: requests-aws-sign (>=0.1.2); extra == 'aws'
